mcpi_addons/PNBT.py
mcpi_addons/__init__.py
mcpi_addons/block.py
mcpi_addons/connection.py
mcpi_addons/entity.py
mcpi_addons/event.py
mcpi_addons/minecraft.py
mcpi_addons/util.py
mcpi_addons/vec3.py
MCPI_Addons-1.2.5.dist-info/METADATA
MCPI_Addons-1.2.5.dist-info/WHEEL
MCPI_Addons-1.2.5.dist-info/top_level.txt
MCPI_Addons-1.2.5.dist-info/RECORD
