Metadata-Version: 2.1
Name: MCPI-Addons
Version: 1.2.5
Summary: An extension of the Minecraft Pi API.
Home-page: https://github.com/Bigjango13/MCPI-Addons
Author: Bigjango13
Classifier: Programming Language :: Python
Classifier: Programming Language :: C++
Classifier: Intended Audience :: Education
Requires-Python: >=3.8
